MANIFEST.in
README.md
setup.py
bi_lstm_crf/__init__.py
bi_lstm_crf/__main__.py
bi_lstm_crf.egg-info/PKG-INFO
bi_lstm_crf.egg-info/SOURCES.txt
bi_lstm_crf.egg-info/dependency_links.txt
bi_lstm_crf.egg-info/requires.txt
bi_lstm_crf.egg-info/top_level.txt
bi_lstm_crf/app/__init__.py
bi_lstm_crf/app/predict.py
bi_lstm_crf/app/train.py
bi_lstm_crf/app/utils.py
bi_lstm_crf/app/preprocessing/__init__.py
bi_lstm_crf/app/preprocessing/preprocess.py
bi_lstm_crf/app/preprocessing/utils.py
bi_lstm_crf/model/__init__.py
bi_lstm_crf/model/crf.py
bi_lstm_crf/model/model.py
bi_lstm_crf/test/__init__.py
bi_lstm_crf/test/test_predict.py