Metadata-Version: 2.1
Name: bi-lstm-crf
Version: 0.2.1
Summary: A PyTorch implementation of the BI-LSTM-CRF model
Home-page: https://github.com/jidasheng/bi-lstm-crf
Author: Dasheng Ji
Author-email: jidasheng@qq.com
License: MIT
Platform: UNKNOWN
Classifier: Programming Language :: Python :: 3
Classifier: License :: OSI Approved :: MIT License
Classifier: Operating System :: OS Independent
